rapid_undistorted/__init__.py
rapid_undistorted/binary_predictor.py
rapid_undistorted/config.yaml
rapid_undistorted/inference.py
rapid_undistorted/unblur_predictor.py
rapid_undistorted/unshadow_predictor.py
rapid_undistorted/unwrap_predictor.py
rapid_undistorted/models/.gitkeep
rapid_undistorted/utils/__init__.py
rapid_undistorted/utils/download_model.py
rapid_undistorted/utils/img_transform.py
rapid_undistorted/utils/infer_engine.py
rapid_undistorted/utils/load_image.py
rapid_undistorted/utils/logger.py
rapid_undistorted-1.0.1.dist-info/METADATA
rapid_undistorted-1.0.1.dist-info/WHEEL
rapid_undistorted-1.0.1.dist-info/top_level.txt
rapid_undistorted-1.0.1.dist-info/RECORD
